{"nodes": [{"id": "c_users_deign_downloads_mathpulse_ai_src_app_tsx", "label": "App.tsx", "file_type": "code", "source_file": "C:\\Users\\Deign\\Downloads\\MATHPULSE-AI\\src\\App.tsx", "source_location": "L1"}, {"id": "src_app_revealshell", "label": "revealShell()", "file_type": "code", "source_file": "C:\\Users\\Deign\\Downloads\\MATHPULSE-AI\\src\\App.tsx", "source_location": "L198"}, {"id": "src_app_checkdiagnostic", "label": "checkDiagnostic()", "file_type": "code", "source_file": "C:\\Users\\Deign\\Downloads\\MATHPULSE-AI\\src\\App.tsx", "source_location": "L279"}, {"id": "src_app_loadsettings", "label": "loadSettings()", "file_type": "code", "source_file": "C:\\Users\\Deign\\Downloads\\MATHPULSE-AI\\src\\App.tsx", "source_location": "L361"}, {"id": "src_app_handlekeydown", "label": "handleKeyDown()", "file_type": "code", "source_file": "C:\\Users\\Deign\\Downloads\\MATHPULSE-AI\\src\\App.tsx", "source_location": "L644"}, {"id": "src_app_handlenotificationnavigate", "label": "handleNotificationNavigate()", "file_type": "code", "source_file": "C:\\Users\\Deign\\Downloads\\MATHPULSE-AI\\src\\App.tsx", "source_location": "L694"}], "edges": [{"source": "c_users_deign_downloads_mathpulse_ai_src_app_tsx", "target": "react", "relation": "imports_from", "context": "import", "confidence": "EXTRACTED", "source_file": "C:\\Users\\Deign\\Downloads\\MATHPULSE-AI\\src\\App.tsx", "source_location": "L1", "weight": 1.0}, {"source": "c_users_deign_downloads_mathpulse_ai_src_app_tsx", "target": "react", "relation": "imports_from", "context": "import", "confidence": "EXTRACTED", "source_file": "C:\\Users\\Deign\\Downloads\\MATHPULSE-AI\\src\\App.tsx", "source_location": "L2", "weight": 1.0}, {"source": "c_users_deign_downloads_mathpulse_ai_src_app_tsx", "target": "c_users_deign_downloads_mathpulse_ai_src_components_apploadingscreen_tsx", "relation": "imports_from", "context": "import", "confidence": "EXTRACTED", "source_file": "C:\\Users\\Deign\\Downloads\\MATHPULSE-AI\\src\\App.tsx", "source_location": "L3", "weight": 1.0}, {"source": "c_users_deign_downloads_mathpulse_ai_src_app_tsx", "target": "c_users_deign_downloads_mathpulse_ai_src_contexts_chatcontext_tsx", "relation": "imports_from", "context": "import", "confidence": "EXTRACTED", "source_file": "C:\\Users\\Deign\\Downloads\\MATHPULSE-AI\\src\\App.tsx", "source_location": "L4", "weight": 1.0}, {"source": "c_users_deign_downloads_mathpulse_ai_src_app_tsx", "target": "contexts_chatcontext_chatprovider", "relation": "imports", "context": "import", "confidence": "EXTRACTED", "source_file": "C:\\Users\\Deign\\Downloads\\MATHPULSE-AI\\src\\App.tsx", "source_location": "L4", "weight": 1.0}, {"source": "c_users_deign_downloads_mathpulse_ai_src_app_tsx", "target": "c_users_deign_downloads_mathpulse_ai_src_contexts_authcontext_tsx", "relation": "imports_from", "context": "import", "confidence": "EXTRACTED", "source_file": "C:\\Users\\Deign\\Downloads\\MATHPULSE-AI\\src\\App.tsx", "source_location": "L5", "weight": 1.0}, {"source": "c_users_deign_downloads_mathpulse_ai_src_app_tsx", "target": "contexts_authcontext_useauth", "relation": "imports", "context": "import", "confidence": "EXTRACTED", "source_file": "C:\\Users\\Deign\\Downloads\\MATHPULSE-AI\\src\\App.tsx", "source_location": "L5", "weight": 1.0}, {"source": "c_users_deign_downloads_mathpulse_ai_src_app_tsx", "target": "c_users_deign_downloads_mathpulse_ai_src_services_authservice_ts", "relation": "imports_from", "context": "import", "confidence": "EXTRACTED", "source_file": "C:\\Users\\Deign\\Downloads\\MATHPULSE-AI\\src\\App.tsx", "source_location": "L6", "weight": 1.0}, {"source": "c_users_deign_downloads_mathpulse_ai_src_app_tsx", "target": "services_authservice_deletecurrentuseraccount", "relation": "imports", "context": "import", "confidence": "EXTRACTED", "source_file": "C:\\Users\\Deign\\Downloads\\MATHPULSE-AI\\src\\App.tsx", "source_location": "L6", "weight": 1.0}, {"source": "c_users_deign_downloads_mathpulse_ai_src_app_tsx", "target": "services_authservice_signoutuser", "relation": "imports", "context": "import", "confidence": "EXTRACTED", "source_file": "C:\\Users\\Deign\\Downloads\\MATHPULSE-AI\\src\\App.tsx", "source_location": "L6", "weight": 1.0}, {"source": "c_users_deign_downloads_mathpulse_ai_src_app_tsx", "target": "services_authservice_updateuserprofile", "relation": "imports", "context": "import", "confidence": "EXTRACTED", "source_file": "C:\\Users\\Deign\\Downloads\\MATHPULSE-AI\\src\\App.tsx", "source_location": "L6", "weight": 1.0}, {"source": "c_users_deign_downloads_mathpulse_ai_src_app_tsx", "target": "services_authservice_updateuserpassword", "relation": "imports", "context": "import", "confidence": "EXTRACTED", "source_file": "C:\\Users\\Deign\\Downloads\\MATHPULSE-AI\\src\\App.tsx", "source_location": "L6", "weight": 1.0}, {"source": "c_users_deign_downloads_mathpulse_ai_src_app_tsx", "target": "c_users_deign_downloads_mathpulse_ai_src_services_notificationservice_ts", "relation": "imports_from", "context": "import", "confidence": "EXTRACTED", "source_file": "C:\\Users\\Deign\\Downloads\\MATHPULSE-AI\\src\\App.tsx", "source_location": "L7", "weight": 1.0}, {"source": "c_users_deign_downloads_mathpulse_ai_src_app_tsx", "target": "services_notificationservice_createnotification", "relation": "imports", "context": "import", "confidence": "EXTRACTED", "source_file": "C:\\Users\\Deign\\Downloads\\MATHPULSE-AI\\src\\App.tsx", "source_location": "L7", "weight": 1.0}, {"source": "c_users_deign_downloads_mathpulse_ai_src_app_tsx", "target": "c_users_deign_downloads_mathpulse_ai_src_services_gamificationservice_ts", "relation": "imports_from", "context": "import", "confidence": "EXTRACTED", "source_file": "C:\\Users\\Deign\\Downloads\\MATHPULSE-AI\\src\\App.tsx", "source_location": "L8", "weight": 1.0}, {"source": "c_users_deign_downloads_mathpulse_ai_src_app_tsx", "target": "services_gamificationservice_updatestreak", "relation": "imports", "context": "import", "confidence": "EXTRACTED", "source_file": "C:\\Users\\Deign\\Downloads\\MATHPULSE-AI\\src\\App.tsx", "source_location": "L8", "weight": 1.0}, {"source": "c_users_deign_downloads_mathpulse_ai_src_app_tsx", "target": "services_gamificationservice_awardxp", "relation": "imports", "context": "import", "confidence": "EXTRACTED", "source_file": "C:\\Users\\Deign\\Downloads\\MATHPULSE-AI\\src\\App.tsx", "source_location": "L8", "weight": 1.0}, {"source": "c_users_deign_downloads_mathpulse_ai_src_app_tsx", "target": "c_users_deign_downloads_mathpulse_ai_src_services_progressservice_ts", "relation": "imports_from", "context": "import", "confidence": "EXTRACTED", "source_file": "C:\\Users\\Deign\\Downloads\\MATHPULSE-AI\\src\\App.tsx", "source_location": "L9", "weight": 1.0}, {"source": "c_users_deign_downloads_mathpulse_ai_src_app_tsx", "target": "services_progressservice_getuserprogress", "relation": "imports", "context": "import", "confidence": "EXTRACTED", "source_file": "C:\\Users\\Deign\\Downloads\\MATHPULSE-AI\\src\\App.tsx", "source_location": "L9", "weight": 1.0}, {"source": "c_users_deign_downloads_mathpulse_ai_src_app_tsx", "target": "c_users_deign_downloads_mathpulse_ai_src_types_models_ts", "relation": "imports_from", "context": "import", "confidence": "EXTRACTED", "source_file": "C:\\Users\\Deign\\Downloads\\MATHPULSE-AI\\src\\App.tsx", "source_location": "L10", "weight": 1.0}, {"source": "c_users_deign_downloads_mathpulse_ai_src_app_tsx", "target": "types_models_adminprofile", "relation": "imports", "context": "import", "confidence": "EXTRACTED", "source_file": "C:\\Users\\Deign\\Downloads\\MATHPULSE-AI\\src\\App.tsx", "source_location": "L10", "weight": 1.0}, {"source": "c_users_deign_downloads_mathpulse_ai_src_app_tsx", "target": "types_models_default_user_settings", "relation": "imports", "context": "import", "confidence": "EXTRACTED", "source_file": "C:\\Users\\Deign\\Downloads\\MATHPULSE-AI\\src\\App.tsx", "source_location": "L10", "weight": 1.0}, {"source": "c_users_deign_downloads_mathpulse_ai_src_app_tsx", "target": "types_models_studentprofile", "relation": "imports", "context": "import", "confidence": "EXTRACTED", "source_file": "C:\\Users\\Deign\\Downloads\\MATHPULSE-AI\\src\\App.tsx", "source_location": "L10", "weight": 1.0}, {"source": "c_users_deign_downloads_mathpulse_ai_src_app_tsx", "target": "types_models_teacherprofile", "relation": "imports", "context": "import", "confidence": "EXTRACTED", "source_file": "C:\\Users\\Deign\\Downloads\\MATHPULSE-AI\\src\\App.tsx", "source_location": "L10", "weight": 1.0}, {"source": "c_users_deign_downloads_mathpulse_ai_src_app_tsx", "target": "types_models_user", "relation": "imports", "context": "import", "confidence": "EXTRACTED", "source_file": "C:\\Users\\Deign\\Downloads\\MATHPULSE-AI\\src\\App.tsx", "source_location": "L10", "weight": 1.0}, {"source": "c_users_deign_downloads_mathpulse_ai_src_app_tsx", "target": "types_models_usersettings", "relation": "imports", "context": "import", "confidence": "EXTRACTED", "source_file": "C:\\Users\\Deign\\Downloads\\MATHPULSE-AI\\src\\App.tsx", "source_location": "L10", "weight": 1.0}, {"source": "c_users_deign_downloads_mathpulse_ai_src_app_tsx", "target": "c_users_deign_downloads_mathpulse_ai_src_services_settingsservice_ts", "relation": "imports_from", "context": "import", "confidence": "EXTRACTED", "source_file": "C:\\Users\\Deign\\Downloads\\MATHPULSE-AI\\src\\App.tsx", "source_location": "L11", "weight": 1.0}, {"source": "c_users_deign_downloads_mathpulse_ai_src_app_tsx", "target": "services_settingsservice_applyruntimesettings", "relation": "imports", "context": "import", "confidence": "EXTRACTED", "source_file": "C:\\Users\\Deign\\Downloads\\MATHPULSE-AI\\src\\App.tsx", "source_location": "L11", "weight": 1.0}, {"source": "c_users_deign_downloads_mathpulse_ai_src_app_tsx", "target": "services_settingsservice_clearclientcache", "relation": "imports", "context": "import", "confidence": "EXTRACTED", "source_file": "C:\\Users\\Deign\\Downloads\\MATHPULSE-AI\\src\\App.tsx", "source_location": "L11", "weight": 1.0}, {"source": "c_users_deign_downloads_mathpulse_ai_src_app_tsx", "target": "services_settingsservice_exportuserdatasnapshot", "relation": "imports", "context": "import", "confidence": "EXTRACTED", "source_file": "C:\\Users\\Deign\\Downloads\\MATHPULSE-AI\\src\\App.tsx", "source_location": "L11", "weight": 1.0}, {"source": "c_users_deign_downloads_mathpulse_ai_src_app_tsx", "target": "services_settingsservice_getusersettings", "relation": "imports", "context": "import", "confidence": "EXTRACTED", "source_file": "C:\\Users\\Deign\\Downloads\\MATHPULSE-AI\\src\\App.tsx", "source_location": "L11", "weight": 1.0}, {"source": "c_users_deign_downloads_mathpulse_ai_src_app_tsx", "target": "services_settingsservice_upsertusersettings", "relation": "imports", "context": "import", "confidence": "EXTRACTED", "source_file": "C:\\Users\\Deign\\Downloads\\MATHPULSE-AI\\src\\App.tsx", "source_location": "L11", "weight": 1.0}, {"source": "c_users_deign_downloads_mathpulse_ai_src_app_tsx", "target": "sonner", "relation": "imports_from", "context": "import", "confidence": "EXTRACTED", "source_file": "C:\\Users\\Deign\\Downloads\\MATHPULSE-AI\\src\\App.tsx", "source_location": "L12", "weight": 1.0}, {"source": "c_users_deign_downloads_mathpulse_ai_src_app_tsx", "target": "c_users_deign_downloads_mathpulse_ai_src_features_notifications", "relation": "imports_from", "context": "import", "confidence": "EXTRACTED", "source_file": "C:\\Users\\Deign\\Downloads\\MATHPULSE-AI\\src\\App.tsx", "source_location": "L13", "weight": 1.0}, {"source": "c_users_deign_downloads_mathpulse_ai_src_app_tsx", "target": "features_notifications_notificationprovider", "relation": "imports", "context": "import", "confidence": "EXTRACTED", "source_file": "C:\\Users\\Deign\\Downloads\\MATHPULSE-AI\\src\\App.tsx", "source_location": "L13", "weight": 1.0}, {"source": "c_users_deign_downloads_mathpulse_ai_src_app_tsx", "target": "lucide_react", "relation": "imports_from", "context": "import", "confidence": "EXTRACTED", "source_file": "C:\\Users\\Deign\\Downloads\\MATHPULSE-AI\\src\\App.tsx", "source_location": "L14", "weight": 1.0}, {"source": "c_users_deign_downloads_mathpulse_ai_src_app_tsx", "target": "c_users_deign_downloads_mathpulse_ai_src_components_useravatar_tsx", "relation": "imports_from", "context": "import", "confidence": "EXTRACTED", "source_file": "C:\\Users\\Deign\\Downloads\\MATHPULSE-AI\\src\\App.tsx", "source_location": "L15", "weight": 1.0}, {"source": "c_users_deign_downloads_mathpulse_ai_src_app_tsx", "target": "c_users_deign_downloads_mathpulse_ai_src_lib_diagnostictopics_ts", "relation": "imports_from", "context": "import", "confidence": "EXTRACTED", "source_file": "C:\\Users\\Deign\\Downloads\\MATHPULSE-AI\\src\\App.tsx", "source_location": "L16", "weight": 1.0}, {"source": "c_users_deign_downloads_mathpulse_ai_src_app_tsx", "target": "lib_diagnostictopics_diagnostictopickey", "relation": "imports", "context": "import", "confidence": "EXTRACTED", "source_file": "C:\\Users\\Deign\\Downloads\\MATHPULSE-AI\\src\\App.tsx", "source_location": "L16", "weight": 1.0}, {"source": "c_users_deign_downloads_mathpulse_ai_src_app_tsx", "target": "lib_diagnostictopics_diagnostic_topic_labels", "relation": "imports", "context": "import", "confidence": "EXTRACTED", "source_file": "C:\\Users\\Deign\\Downloads\\MATHPULSE-AI\\src\\App.tsx", "source_location": "L16", "weight": 1.0}, {"source": "c_users_deign_downloads_mathpulse_ai_src_app_tsx", "target": "lib_diagnostictopics_normalizediagnostictopic", "relation": "imports", "context": "import", "confidence": "EXTRACTED", "source_file": "C:\\Users\\Deign\\Downloads\\MATHPULSE-AI\\src\\App.tsx", "source_location": "L16", "weight": 1.0}, {"source": "c_users_deign_downloads_mathpulse_ai_src_app_tsx", "target": "c_users_deign_downloads_mathpulse_ai_src_data_curriculummodules", "relation": "imports_from", "context": "import", "confidence": "EXTRACTED", "source_file": "C:\\Users\\Deign\\Downloads\\MATHPULSE-AI\\src\\App.tsx", "source_location": "L17", "weight": 1.0}, {"source": "c_users_deign_downloads_mathpulse_ai_src_app_tsx", "target": "data_curriculummodules_getcurriculummodulesforlearner", "relation": "imports", "context": "import", "confidence": "EXTRACTED", "source_file": "C:\\Users\\Deign\\Downloads\\MATHPULSE-AI\\src\\App.tsx", "source_location": "L17", "weight": 1.0}, {"source": "c_users_deign_downloads_mathpulse_ai_src_app_tsx", "target": "data_curriculummodules_resolvelearnergradelevel", "relation": "imports", "context": "import", "confidence": "EXTRACTED", "source_file": "C:\\Users\\Deign\\Downloads\\MATHPULSE-AI\\src\\App.tsx", "source_location": "L17", "weight": 1.0}, {"source": "c_users_deign_downloads_mathpulse_ai_src_app_tsx", "target": "firestore", "relation": "imports_from", "context": "import", "confidence": "EXTRACTED", "source_file": "C:\\Users\\Deign\\Downloads\\MATHPULSE-AI\\src\\App.tsx", "source_location": "L18", "weight": 1.0}, {"source": "c_users_deign_downloads_mathpulse_ai_src_app_tsx", "target": "c_users_deign_downloads_mathpulse_ai_src_lib_firebase", "relation": "imports_from", "context": "import", "confidence": "EXTRACTED", "source_file": "C:\\Users\\Deign\\Downloads\\MATHPULSE-AI\\src\\App.tsx", "source_location": "L19", "weight": 1.0}, {"source": "c_users_deign_downloads_mathpulse_ai_src_app_tsx", "target": "lib_firebase_db", "relation": "imports", "context": "import", "confidence": "EXTRACTED", "source_file": "C:\\Users\\Deign\\Downloads\\MATHPULSE-AI\\src\\App.tsx", "source_location": "L19", "weight": 1.0}, {"source": "c_users_deign_downloads_mathpulse_ai_src_app_tsx", "target": "src_app_revealshell", "relation": "contains", "confidence": "EXTRACTED", "source_file": "C:\\Users\\Deign\\Downloads\\MATHPULSE-AI\\src\\App.tsx", "source_location": "L198", "weight": 1.0}, {"source": "c_users_deign_downloads_mathpulse_ai_src_app_tsx", "target": "src_app_checkdiagnostic", "relation": "contains", "confidence": "EXTRACTED", "source_file": "C:\\Users\\Deign\\Downloads\\MATHPULSE-AI\\src\\App.tsx", "source_location": "L279", "weight": 1.0}, {"source": "c_users_deign_downloads_mathpulse_ai_src_app_tsx", "target": "src_app_loadsettings", "relation": "contains", "confidence": "EXTRACTED", "source_file": "C:\\Users\\Deign\\Downloads\\MATHPULSE-AI\\src\\App.tsx", "source_location": "L361", "weight": 1.0}, {"source": "c_users_deign_downloads_mathpulse_ai_src_app_tsx", "target": "src_app_handlekeydown", "relation": "contains", "confidence": "EXTRACTED", "source_file": "C:\\Users\\Deign\\Downloads\\MATHPULSE-AI\\src\\App.tsx", "source_location": "L644", "weight": 1.0}, {"source": "c_users_deign_downloads_mathpulse_ai_src_app_tsx", "target": "src_app_handlenotificationnavigate", "relation": "contains", "confidence": "EXTRACTED", "source_file": "C:\\Users\\Deign\\Downloads\\MATHPULSE-AI\\src\\App.tsx", "source_location": "L694", "weight": 1.0}], "raw_calls": [{"caller_nid": "src_app_revealshell", "callee": "setDashboardShellDeferredReady", "is_member_call": false, "source_file": "C:\\Users\\Deign\\Downloads\\MATHPULSE-AI\\src\\App.tsx", "source_location": "L200"}, {"caller_nid": "src_app_checkdiagnostic", "callee": "getDoc", "is_member_call": false, "source_file": "C:\\Users\\Deign\\Downloads\\MATHPULSE-AI\\src\\App.tsx", "source_location": "L281"}, {"caller_nid": "src_app_checkdiagnostic", "callee": "doc", "is_member_call": false, "source_file": "C:\\Users\\Deign\\Downloads\\MATHPULSE-AI\\src\\App.tsx", "source_location": "L281"}, {"caller_nid": "src_app_checkdiagnostic", "callee": "exists", "is_member_call": true, "source_file": "C:\\Users\\Deign\\Downloads\\MATHPULSE-AI\\src\\App.tsx", "source_location": "L283"}, {"caller_nid": "src_app_checkdiagnostic", "callee": "data", "is_member_call": true, "source_file": "C:\\Users\\Deign\\Downloads\\MATHPULSE-AI\\src\\App.tsx", "source_location": "L283"}, {"caller_nid": "src_app_checkdiagnostic", "callee": "setHasCompletedDiagnostic", "is_member_call": false, "source_file": "C:\\Users\\Deign\\Downloads\\MATHPULSE-AI\\src\\App.tsx", "source_location": "L284"}, {"caller_nid": "src_app_checkdiagnostic", "callee": "setTimeout", "is_member_call": false, "source_file": "C:\\Users\\Deign\\Downloads\\MATHPULSE-AI\\src\\App.tsx", "source_location": "L285"}, {"caller_nid": "src_app_checkdiagnostic", "callee": "data", "is_member_call": true, "source_file": "C:\\Users\\Deign\\Downloads\\MATHPULSE-AI\\src\\App.tsx", "source_location": "L289"}, {"caller_nid": "src_app_checkdiagnostic", "callee": "setHasCompletedDiagnostic", "is_member_call": false, "source_file": "C:\\Users\\Deign\\Downloads\\MATHPULSE-AI\\src\\App.tsx", "source_location": "L290"}, {"caller_nid": "src_app_checkdiagnostic", "callee": "data", "is_member_call": true, "source_file": "C:\\Users\\Deign\\Downloads\\MATHPULSE-AI\\src\\App.tsx", "source_location": "L291"}, {"caller_nid": "src_app_checkdiagnostic", "callee": "setAtRiskSubjects", "is_member_call": false, "source_file": "C:\\Users\\Deign\\Downloads\\MATHPULSE-AI\\src\\App.tsx", "source_location": "L293"}, {"caller_nid": "src_app_checkdiagnostic", "callee": "setPriorityTopics", "is_member_call": false, "source_file": "C:\\Users\\Deign\\Downloads\\MATHPULSE-AI\\src\\App.tsx", "source_location": "L294"}, {"caller_nid": "src_app_checkdiagnostic", "callee": "error", "is_member_call": true, "source_file": "C:\\Users\\Deign\\Downloads\\MATHPULSE-AI\\src\\App.tsx", "source_location": "L298"}, {"caller_nid": "src_app_loadsettings", "callee": "setUserSettings", "is_member_call": false, "source_file": "C:\\Users\\Deign\\Downloads\\MATHPULSE-AI\\src\\App.tsx", "source_location": "L363"}, {"caller_nid": "src_app_loadsettings", "callee": "getUserSettings", "is_member_call": false, "source_file": "C:\\Users\\Deign\\Downloads\\MATHPULSE-AI\\src\\App.tsx", "source_location": "L368"}, {"caller_nid": "src_app_loadsettings", "callee": "setUserSettings", "is_member_call": false, "source_file": "C:\\Users\\Deign\\Downloads\\MATHPULSE-AI\\src\\App.tsx", "source_location": "L369"}, {"caller_nid": "src_app_loadsettings", "callee": "error", "is_member_call": true, "source_file": "C:\\Users\\Deign\\Downloads\\MATHPULSE-AI\\src\\App.tsx", "source_location": "L371"}, {"caller_nid": "src_app_loadsettings", "callee": "setUserSettings", "is_member_call": false, "source_file": "C:\\Users\\Deign\\Downloads\\MATHPULSE-AI\\src\\App.tsx", "source_location": "L372"}, {"caller_nid": "src_app_handlekeydown", "callee": "toLowerCase", "is_member_call": true, "source_file": "C:\\Users\\Deign\\Downloads\\MATHPULSE-AI\\src\\App.tsx", "source_location": "L649"}, {"caller_nid": "src_app_handlekeydown", "callee": "preventDefault", "is_member_call": true, "source_file": "C:\\Users\\Deign\\Downloads\\MATHPULSE-AI\\src\\App.tsx", "source_location": "L651"}, {"caller_nid": "src_app_handlekeydown", "callee": "handleStudentNavigation", "is_member_call": false, "source_file": "C:\\Users\\Deign\\Downloads\\MATHPULSE-AI\\src\\App.tsx", "source_location": "L652"}, {"caller_nid": "src_app_handlekeydown", "callee": "preventDefault", "is_member_call": true, "source_file": "C:\\Users\\Deign\\Downloads\\MATHPULSE-AI\\src\\App.tsx", "source_location": "L655"}, {"caller_nid": "src_app_handlekeydown", "callee": "handleStudentNavigation", "is_member_call": false, "source_file": "C:\\Users\\Deign\\Downloads\\MATHPULSE-AI\\src\\App.tsx", "source_location": "L656"}, {"caller_nid": "src_app_handlekeydown", "callee": "preventDefault", "is_member_call": true, "source_file": "C:\\Users\\Deign\\Downloads\\MATHPULSE-AI\\src\\App.tsx", "source_location": "L659"}, {"caller_nid": "src_app_handlekeydown", "callee": "handleStudentNavigation", "is_member_call": false, "source_file": "C:\\Users\\Deign\\Downloads\\MATHPULSE-AI\\src\\App.tsx", "source_location": "L660"}, {"caller_nid": "src_app_handlekeydown", "callee": "preventDefault", "is_member_call": true, "source_file": "C:\\Users\\Deign\\Downloads\\MATHPULSE-AI\\src\\App.tsx", "source_location": "L663"}, {"caller_nid": "src_app_handlekeydown", "callee": "handleStudentNavigation", "is_member_call": false, "source_file": "C:\\Users\\Deign\\Downloads\\MATHPULSE-AI\\src\\App.tsx", "source_location": "L664"}, {"caller_nid": "src_app_handlekeydown", "callee": "preventDefault", "is_member_call": true, "source_file": "C:\\Users\\Deign\\Downloads\\MATHPULSE-AI\\src\\App.tsx", "source_location": "L667"}, {"caller_nid": "src_app_handlekeydown", "callee": "handleStudentNavigation", "is_member_call": false, "source_file": "C:\\Users\\Deign\\Downloads\\MATHPULSE-AI\\src\\App.tsx", "source_location": "L668"}, {"caller_nid": "src_app_handlekeydown", "callee": "preventDefault", "is_member_call": true, "source_file": "C:\\Users\\Deign\\Downloads\\MATHPULSE-AI\\src\\App.tsx", "source_location": "L671"}, {"caller_nid": "src_app_handlekeydown", "callee": "setShowSettingsModal", "is_member_call": false, "source_file": "C:\\Users\\Deign\\Downloads\\MATHPULSE-AI\\src\\App.tsx", "source_location": "L672"}, {"caller_nid": "src_app_handlekeydown", "callee": "preventDefault", "is_member_call": true, "source_file": "C:\\Users\\Deign\\Downloads\\MATHPULSE-AI\\src\\App.tsx", "source_location": "L675"}, {"caller_nid": "src_app_handlekeydown", "callee": "setShowProfileModal", "is_member_call": false, "source_file": "C:\\Users\\Deign\\Downloads\\MATHPULSE-AI\\src\\App.tsx", "source_location": "L676"}, {"caller_nid": "src_app_handlekeydown", "callee": "preventDefault", "is_member_call": true, "source_file": "C:\\Users\\Deign\\Downloads\\MATHPULSE-AI\\src\\App.tsx", "source_location": "L679"}, {"caller_nid": "src_app_handlekeydown", "callee": "setShowCalculator", "is_member_call": false, "source_file": "C:\\Users\\Deign\\Downloads\\MATHPULSE-AI\\src\\App.tsx", "source_location": "L680"}, {"caller_nid": "src_app_handlenotificationnavigate", "callee": "handleStudentNavigation", "is_member_call": false, "source_file": "C:\\Users\\Deign\\Downloads\\MATHPULSE-AI\\src\\App.tsx", "source_location": "L697"}]}