{"nodes": [{"id": "c_users_deign_downloads_mathpulse_ai_src_components_masteryheatmap_tsx", "label": "MasteryHeatmap.tsx", "file_type": "code", "source_file": "C:\\Users\\Deign\\Downloads\\MATHPULSE-AI\\src\\components\\MasteryHeatmap.tsx", "source_location": "L1"}, {"id": "components_masteryheatmap_getmasterycolor", "label": "getMasteryColor()", "file_type": "code", "source_file": "C:\\Users\\Deign\\Downloads\\MATHPULSE-AI\\src\\components\\MasteryHeatmap.tsx", "source_location": "L81"}, {"id": "components_masteryheatmap_getmasterytextcolor", "label": "getMasteryTextColor()", "file_type": "code", "source_file": "C:\\Users\\Deign\\Downloads\\MATHPULSE-AI\\src\\components\\MasteryHeatmap.tsx", "source_location": "L90"}], "edges": [{"source": "c_users_deign_downloads_mathpulse_ai_src_components_masteryheatmap_tsx", "target": "react", "relation": "imports_from", "context": "import", "confidence": "EXTRACTED", "source_file": "C:\\Users\\Deign\\Downloads\\MATHPULSE-AI\\src\\components\\MasteryHeatmap.tsx", "source_location": "L1", "weight": 1.0}, {"source": "c_users_deign_downloads_mathpulse_ai_src_components_masteryheatmap_tsx", "target": "react_query", "relation": "imports_from", "context": "import", "confidence": "EXTRACTED", "source_file": "C:\\Users\\Deign\\Downloads\\MATHPULSE-AI\\src\\components\\MasteryHeatmap.tsx", "source_location": "L2", "weight": 1.0}, {"source": "c_users_deign_downloads_mathpulse_ai_src_components_masteryheatmap_tsx", "target": "react", "relation": "imports_from", "context": "import", "confidence": "EXTRACTED", "source_file": "C:\\Users\\Deign\\Downloads\\MATHPULSE-AI\\src\\components\\MasteryHeatmap.tsx", "source_location": "L3", "weight": 1.0}, {"source": "c_users_deign_downloads_mathpulse_ai_src_components_masteryheatmap_tsx", "target": "lucide_react", "relation": "imports_from", "context": "import", "confidence": "EXTRACTED", "source_file": "C:\\Users\\Deign\\Downloads\\MATHPULSE-AI\\src\\components\\MasteryHeatmap.tsx", "source_location": "L4", "weight": 1.0}, {"source": "c_users_deign_downloads_mathpulse_ai_src_components_masteryheatmap_tsx", "target": "firestore", "relation": "imports_from", "context": "import", "confidence": "EXTRACTED", "source_file": "C:\\Users\\Deign\\Downloads\\MATHPULSE-AI\\src\\components\\MasteryHeatmap.tsx", "source_location": "L5", "weight": 1.0}, {"source": "c_users_deign_downloads_mathpulse_ai_src_components_masteryheatmap_tsx", "target": "c_users_deign_downloads_mathpulse_ai_src_lib_firebase", "relation": "imports_from", "context": "import", "confidence": "EXTRACTED", "source_file": "C:\\Users\\Deign\\Downloads\\MATHPULSE-AI\\src\\components\\MasteryHeatmap.tsx", "source_location": "L6", "weight": 1.0}, {"source": "c_users_deign_downloads_mathpulse_ai_src_components_masteryheatmap_tsx", "target": "lib_firebase_db", "relation": "imports", "context": "import", "confidence": "EXTRACTED", "source_file": "C:\\Users\\Deign\\Downloads\\MATHPULSE-AI\\src\\components\\MasteryHeatmap.tsx", "source_location": "L6", "weight": 1.0}, {"source": "c_users_deign_downloads_mathpulse_ai_src_components_masteryheatmap_tsx", "target": "c_users_deign_downloads_mathpulse_ai_src_utils_cachekeys", "relation": "imports_from", "context": "import", "confidence": "EXTRACTED", "source_file": "C:\\Users\\Deign\\Downloads\\MATHPULSE-AI\\src\\components\\MasteryHeatmap.tsx", "source_location": "L7", "weight": 1.0}, {"source": "c_users_deign_downloads_mathpulse_ai_src_components_masteryheatmap_tsx", "target": "utils_cachekeys_cachekeys", "relation": "imports", "context": "import", "confidence": "EXTRACTED", "source_file": "C:\\Users\\Deign\\Downloads\\MATHPULSE-AI\\src\\components\\MasteryHeatmap.tsx", "source_location": "L7", "weight": 1.0}, {"source": "c_users_deign_downloads_mathpulse_ai_src_components_masteryheatmap_tsx", "target": "components_masteryheatmap_getmasterycolor", "relation": "contains", "confidence": "EXTRACTED", "source_file": "C:\\Users\\Deign\\Downloads\\MATHPULSE-AI\\src\\components\\MasteryHeatmap.tsx", "source_location": "L81", "weight": 1.0}, {"source": "c_users_deign_downloads_mathpulse_ai_src_components_masteryheatmap_tsx", "target": "components_masteryheatmap_getmasterytextcolor", "relation": "contains", "confidence": "EXTRACTED", "source_file": "C:\\Users\\Deign\\Downloads\\MATHPULSE-AI\\src\\components\\MasteryHeatmap.tsx", "source_location": "L90", "weight": 1.0}], "raw_calls": []}