{"nodes": [{"id": "c_users_deign_downloads_mathpulse_ai_functions_src_services_backendapi_ts", "label": "backendApi.ts", "file_type": "code", "source_file": "C:\\Users\\Deign\\Downloads\\MATHPULSE-AI\\functions\\src\\services\\backendApi.ts", "source_location": "L1"}, {"id": "services_backendapi_callwithretry", "label": "callWithRetry()", "file_type": "code", "source_file": "C:\\Users\\Deign\\Downloads\\MATHPULSE-AI\\functions\\src\\services\\backendApi.ts", "source_location": "L50"}, {"id": "services_backendapi_predictrisk", "label": "predictRisk()", "file_type": "code", "source_file": "C:\\Users\\Deign\\Downloads\\MATHPULSE-AI\\functions\\src\\services\\backendApi.ts", "source_location": "L104"}, {"id": "services_backendapi_generatelearningpath", "label": "generateLearningPath()", "file_type": "code", "source_file": "C:\\Users\\Deign\\Downloads\\MATHPULSE-AI\\functions\\src\\services\\backendApi.ts", "source_location": "L114"}, {"id": "services_backendapi_callbackendapi", "label": "callBackendApi()", "file_type": "code", "source_file": "C:\\Users\\Deign\\Downloads\\MATHPULSE-AI\\functions\\src\\services\\backendApi.ts", "source_location": "L124"}], "edges": [{"source": "c_users_deign_downloads_mathpulse_ai_functions_src_services_backendapi_ts", "target": "axios", "relation": "imports_from", "context": "import", "confidence": "EXTRACTED", "source_file": "C:\\Users\\Deign\\Downloads\\MATHPULSE-AI\\functions\\src\\services\\backendApi.ts", "source_location": "L9", "weight": 1.0}, {"source": "c_users_deign_downloads_mathpulse_ai_functions_src_services_backendapi_ts", "target": "firebase_functions", "relation": "imports_from", "context": "import", "confidence": "EXTRACTED", "source_file": "C:\\Users\\Deign\\Downloads\\MATHPULSE-AI\\functions\\src\\services\\backendApi.ts", "source_location": "L10", "weight": 1.0}, {"source": "c_users_deign_downloads_mathpulse_ai_functions_src_services_backendapi_ts", "target": "c_users_deign_downloads_mathpulse_ai_functions_src_config_constants", "relation": "imports_from", "context": "import", "confidence": "EXTRACTED", "source_file": "C:\\Users\\Deign\\Downloads\\MATHPULSE-AI\\functions\\src\\services\\backendApi.ts", "source_location": "L11", "weight": 1.0}, {"source": "c_users_deign_downloads_mathpulse_ai_functions_src_services_backendapi_ts", "target": "config_constants_backend_api_url", "relation": "imports", "context": "import", "confidence": "EXTRACTED", "source_file": "C:\\Users\\Deign\\Downloads\\MATHPULSE-AI\\functions\\src\\services\\backendApi.ts", "source_location": "L11", "weight": 1.0}, {"source": "c_users_deign_downloads_mathpulse_ai_functions_src_services_backendapi_ts", "target": "config_constants_backend_timeout_ms", "relation": "imports", "context": "import", "confidence": "EXTRACTED", "source_file": "C:\\Users\\Deign\\Downloads\\MATHPULSE-AI\\functions\\src\\services\\backendApi.ts", "source_location": "L11", "weight": 1.0}, {"source": "c_users_deign_downloads_mathpulse_ai_functions_src_services_backendapi_ts", "target": "config_constants_max_retries", "relation": "imports", "context": "import", "confidence": "EXTRACTED", "source_file": "C:\\Users\\Deign\\Downloads\\MATHPULSE-AI\\functions\\src\\services\\backendApi.ts", "source_location": "L11", "weight": 1.0}, {"source": "c_users_deign_downloads_mathpulse_ai_functions_src_services_backendapi_ts", "target": "services_backendapi_callwithretry", "relation": "contains", "confidence": "EXTRACTED", "source_file": "C:\\Users\\Deign\\Downloads\\MATHPULSE-AI\\functions\\src\\services\\backendApi.ts", "source_location": "L50", "weight": 1.0}, {"source": "c_users_deign_downloads_mathpulse_ai_functions_src_services_backendapi_ts", "target": "services_backendapi_predictrisk", "relation": "contains", "confidence": "EXTRACTED", "source_file": "C:\\Users\\Deign\\Downloads\\MATHPULSE-AI\\functions\\src\\services\\backendApi.ts", "source_location": "L104", "weight": 1.0}, {"source": "c_users_deign_downloads_mathpulse_ai_functions_src_services_backendapi_ts", "target": "services_backendapi_generatelearningpath", "relation": "contains", "confidence": "EXTRACTED", "source_file": "C:\\Users\\Deign\\Downloads\\MATHPULSE-AI\\functions\\src\\services\\backendApi.ts", "source_location": "L114", "weight": 1.0}, {"source": "c_users_deign_downloads_mathpulse_ai_functions_src_services_backendapi_ts", "target": "services_backendapi_callbackendapi", "relation": "contains", "confidence": "EXTRACTED", "source_file": "C:\\Users\\Deign\\Downloads\\MATHPULSE-AI\\functions\\src\\services\\backendApi.ts", "source_location": "L124", "weight": 1.0}, {"source": "services_backendapi_predictrisk", "target": "services_backendapi_callwithretry", "relation": "calls", "context": "call", "confidence": "EXTRACTED", "source_file": "C:\\Users\\Deign\\Downloads\\MATHPULSE-AI\\functions\\src\\services\\backendApi.ts", "source_location": "L107", "weight": 1.0}, {"source": "services_backendapi_generatelearningpath", "target": "services_backendapi_callwithretry", "relation": "calls", "context": "call", "confidence": "EXTRACTED", "source_file": "C:\\Users\\Deign\\Downloads\\MATHPULSE-AI\\functions\\src\\services\\backendApi.ts", "source_location": "L117", "weight": 1.0}, {"source": "services_backendapi_callbackendapi", "target": "services_backendapi_callwithretry", "relation": "calls", "context": "call", "confidence": "EXTRACTED", "source_file": "C:\\Users\\Deign\\Downloads\\MATHPULSE-AI\\functions\\src\\services\\backendApi.ts", "source_location": "L128", "weight": 1.0}], "raw_calls": [{"caller_nid": "services_backendapi_callwithretry", "callee": "await axios.post", "is_member_call": false, "source_file": "C:\\Users\\Deign\\Downloads\\MATHPULSE-AI\\functions\\src\\services\\backendApi.ts", "source_location": "L59"}, {"caller_nid": "services_backendapi_callwithretry", "callee": "error", "is_member_call": true, "source_file": "C:\\Users\\Deign\\Downloads\\MATHPULSE-AI\\functions\\src\\services\\backendApi.ts", "source_location": "L70"}, {"caller_nid": "services_backendapi_callwithretry", "callee": "pow", "is_member_call": true, "source_file": "C:\\Users\\Deign\\Downloads\\MATHPULSE-AI\\functions\\src\\services\\backendApi.ts", "source_location": "L78"}, {"caller_nid": "services_backendapi_callwithretry", "callee": "warn", "is_member_call": true, "source_file": "C:\\Users\\Deign\\Downloads\\MATHPULSE-AI\\functions\\src\\services\\backendApi.ts", "source_location": "L79"}, {"caller_nid": "services_backendapi_callwithretry", "callee": "error", "is_member_call": true, "source_file": "C:\\Users\\Deign\\Downloads\\MATHPULSE-AI\\functions\\src\\services\\backendApi.ts", "source_location": "L85"}]}